facepixellate/__init__.py
facepixellate/facepixellate.py
facepixellate/haarcascade_frontalface_default.xml
facepixellate-1.3.1.dist-info/LICENSE
facepixellate-1.3.1.dist-info/METADATA
facepixellate-1.3.1.dist-info/WHEEL
facepixellate-1.3.1.dist-info/top_level.txt
facepixellate-1.3.1.dist-info/RECORD
