Metadata-Version: 2.1
Name: facepixellate
Version: 1.3.1
Summary: Detect and pixellate faces in the picture
Home-page: https://github.com/tomtillo/facepixellate
Author: Tom Tillo
Author-email: tomtillo@gmail.com
License: UNKNOWN
Platform: UNKNOWN
Classifier: Programming Language :: Python :: 3
Classifier: Programming Language :: Python :: 3.6
Classifier: License :: OSI Approved :: MIT License
Classifier: Operating System :: OS Independent
Requires-Python: >=3.6
Requires-Dist: opencv-python
